dobotapi/__init__.py
dobotapi/conveyor_belt/belt.py
dobotapi/dobot.py
dobotapi/dobot_interfaces.py
dobotapi/dobot_message.py
dobotapi/drawing/svg_handler.py
dobotapi/effectors/gripper.py
dobotapi/effectors/suctioncup.py
dobotapi/exceptions.py
dobotapi/shell.py
dobotapi/utils.py
dobotapi-0.0.3.dist-info/LICENSE
dobotapi-0.0.3.dist-info/METADATA
dobotapi-0.0.3.dist-info/WHEEL
dobotapi-0.0.3.dist-info/RECORD
