Metadata-Version: 2.1
Name: dobotapi
Version: 0.0.3
Summary: Python API for controlling Dobot Magician and it's addons
Home-page: https://github.com/Stax124/DobotAPI
License: MIT
Keywords: dobot,magician,api,python
Author: Stax124
Author-email: tamoncz@gmail.com
Requires-Python: >=3.9,<4.0
Classifier: License :: OSI Approved :: MIT License
Classifier: Programming Language :: Python :: 3
Classifier: Programming Language :: Python :: 3.9
Classifier: Programming Language :: Python :: 3.10
Classifier: Programming Language :: Python :: 3.11
Requires-Dist: coloredlogs (>=15.0.1,<16.0.0)
Requires-Dist: prompt-toolkit (>=3.0.29,<4.0.0)
Requires-Dist: pyserial (>=3.5,<4.0)
Requires-Dist: svg.path (>=6.2,<7.0)
Project-URL: Documentation, https://stax124.github.io/DobotAPI/
Project-URL: Repository, https://github.com/Stax124/DobotAPI
